MANIFEST.in
README.md
requirements.txt
setup.py
funcat/VERSION.txt
funcat/__init__.py
funcat/__init__.pyc
funcat/api.py
funcat/api.pyc
funcat/context.py
funcat/context.pyc
funcat/func.py
funcat/func.pyc
funcat/helper.py
funcat/helper.pyc
funcat/indicators.py
funcat/indicators.pyc
funcat/time_series.py
funcat/time_series.pyc
funcat/utils.py
funcat/utils.pyc
funcat.egg-info/PKG-INFO
funcat.egg-info/SOURCES.txt
funcat.egg-info/dependency_links.txt
funcat.egg-info/not-zip-safe
funcat.egg-info/requires.txt
funcat.egg-info/top_level.txt
funcat/data/__init__.py
funcat/data/__init__.pyc
funcat/data/backend.py
funcat/data/backend.pyc
funcat/data/rqalpha_data_backend.py
funcat/data/rqdata_data_backend.py
funcat/data/tushare_backend.py
funcat/data/tushare_backend.pyc